klaviyo/__init__.py
klaviyo/api.py
klaviyo/api_helper.py
klaviyo/campaigns.py
klaviyo/data_privacy.py
klaviyo/exceptions.py
klaviyo/lists.py
klaviyo/metrics.py
klaviyo/middleware.py
klaviyo/profiles.py
klaviyo/public.py
tests/__init__.py
tests/test_api_helper.py
tests/test_data_privacy.py
tests/test_public.py
tests/fixtures/__init__.py
tests/fixtures/api_helper.py
tests/fixtures/data_privacy.py
tests/fixtures/public.py
klaviyo-3.1.7.dist-info/METADATA
klaviyo-3.1.7.dist-info/WHEEL
klaviyo-3.1.7.dist-info/top_level.txt
klaviyo-3.1.7.dist-info/RECORD
