Metadata-Version: 2.1
Name: klaviyo
Version: 3.1.7
Summary: Deprecated Klaviyo SDK
Home-page: http://github.com/klaviyo/python-klaviyo
Author: Klaviyo
Author-email: developers@klaviyo.com
License: MIT License
Keywords: klaviyo
Requires-Dist: requests (>=2.2.1)
Requires-Dist: simplejson (>=3.17.0)
